openssl_engine/__init__.py
openssl_engine/sslcontext.py
openssl_engine/utils.py
openssl_engine-1.3.1.dist-info/METADATA
openssl_engine-1.3.1.dist-info/WHEEL
openssl_engine-1.3.1.dist-info/top_level.txt
openssl_engine-1.3.1.dist-info/RECORD
