Metadata-Version: 2.1
Name: openssl-engine
Version: 1.3.1
Summary: Python openssl engine support
Home-page: https://github.com/jose-pr/pypki
Author: Jose A.
Author-email: jose-pr@coqui.dev
License: UNKNOWN
Platform: UNKNOWN
Requires-Dist: pyopenssl
Requires-Dist: cryptography (>=36)
Requires-Dist: sslcontext (>=1.4.0) ; extra == "sslcontext"
